authlete/django/__init__.py
authlete/django/handler/__init__.py
authlete/django/handler/authorization_request_base_handler.py
authlete/django/handler/authorization_request_decision_handler.py
authlete/django/handler/authorization_request_error_handler.py
authlete/django/handler/base_request_handler.py
authlete/django/handler/claim_collector.py
authlete/django/handler/configuration_request_handler.py
authlete/django/handler/credential_issuer_jwks_request_handler.py
authlete/django/handler/credential_issuer_metadata_request_handler.py
authlete/django/handler/credential_jwt_issuer_metadata_request_handler.py
authlete/django/handler/federation_configuration_request_handler.py
authlete/django/handler/federation_registration_request_handler.py
authlete/django/handler/introspection_request_handler.py
authlete/django/handler/jwks_request_handler.py
authlete/django/handler/no_interaction_handler.py
authlete/django/handler/par_request_handler.py
authlete/django/handler/revocation_request_handler.py
authlete/django/handler/token_request_base_handler.py
authlete/django/handler/token_request_handler.py
authlete/django/handler/userinfo_request_handler.py
authlete/django/handler/spi/__init__.py
authlete/django/handler/spi/authorization_request_decision_handler_spi.py
authlete/django/handler/spi/authorization_request_decision_handler_spi_adapter.py
authlete/django/handler/spi/authorization_request_handler_spi.py
authlete/django/handler/spi/authorization_request_handler_spi_adapter.py
authlete/django/handler/spi/no_interaction_handler_spi.py
authlete/django/handler/spi/no_interaction_handler_spi_adapter.py
authlete/django/handler/spi/token_request_handler_spi.py
authlete/django/handler/spi/token_request_handler_spi_adapter.py
authlete/django/handler/spi/user_claim_provider_spi.py
authlete/django/handler/spi/user_claim_provider_spi_adapter.py
authlete/django/handler/spi/userinfo_request_handler_spi.py
authlete/django/handler/spi/userinfo_request_handler_spi_adapter.py
authlete_django-1.1.1.dist-info/METADATA
authlete_django-1.1.1.dist-info/WHEEL
authlete_django-1.1.1.dist-info/licenses/LICENSE
authlete_django-1.1.1.dist-info/RECORD
