Metadata-Version: 2.1
Name: authlete-django
Version: 1.1.1
Summary: Django library for Authlete
Project-URL: Homepage, https://www.authlete.com/
Project-URL: Repository, https://github.com/authlete/authlete-python-django.git
Author-email: "Authlete, Inc." <admin@authlete.com>
License: 
License-File: LICENSE
Keywords: Django,OAuth,OAuth 2.0,OIDC,OpenID,OpenID Connect
Classifier: License :: OSI Approved :: Apache Software License
Classifier: Operating System :: OS Independent
Classifier: Programming Language :: Python :: 3
Classifier: Topic :: Security
Requires-Python: >=3.8
Requires-Dist: authlete>=1.3.0
